LICENSE.txt
MANIFEST.in
README.md
setup.cfg
setup.py
bin/zounds-quickstart
zounds/__init__.py
zounds.egg-info/PKG-INFO
zounds.egg-info/SOURCES.txt
zounds.egg-info/dependency_links.txt
zounds.egg-info/requires.txt
zounds.egg-info/top_level.txt
zounds/basic/__init__.py
zounds/basic/audiograph.py
zounds/basic/basic.py
zounds/basic/fuzz_test.py
zounds/basic/test_audiograph.py
zounds/basic/test_integration.py
zounds/basic/test_merge.py
zounds/basic/util.py
zounds/core/__init__.py
zounds/core/axis.py
zounds/core/dimensions.py
zounds/core/test_core.py
zounds/core/test_identitydimension.py
zounds/datasets/__init__.py
zounds/datasets/cache.py
zounds/datasets/composite.py
zounds/datasets/filesystem.py
zounds/datasets/freesound.py
zounds/datasets/ingest.py
zounds/datasets/internetarchive.py
zounds/datasets/musicnet.py
zounds/datasets/nsynth.py
zounds/datasets/phatdrumloops.py
zounds/datasets/predownload.py
zounds/datasets/test_composite.py
zounds/datasets/test_predownload.py
zounds/datasets/util.py
zounds/index/__init__.py
zounds/index/brute_force.py
zounds/index/hammingdb.py
zounds/index/index.py
zounds/index/test_hammingdb.py
zounds/index/test_hammingindex.py
zounds/learn/__init__.py
zounds/learn/dct_transform.py
zounds/learn/embedding.py
zounds/learn/functional.py
zounds/learn/gan_experiment.py
zounds/learn/gated.py
zounds/learn/graph.py
zounds/learn/learn.py
zounds/learn/loss.py
zounds/learn/multiresolution.py
zounds/learn/preprocess.py
zounds/learn/pytorch_model.py
zounds/learn/random_samples.py
zounds/learn/sample_embedding.py
zounds/learn/sinclayer.py
zounds/learn/sklearn_preprocessor.py
zounds/learn/spectral.py
zounds/learn/supervised.py
zounds/learn/test_dct.py
zounds/learn/test_embedding.py
zounds/learn/test_instancescaling.py
zounds/learn/test_learn.py
zounds/learn/test_log.py
zounds/learn/test_meanstd.py
zounds/learn/test_multiply.py
zounds/learn/test_pipeline.py
zounds/learn/test_pytorch_model.py
zounds/learn/test_random_samples.py
zounds/learn/test_reshape.py
zounds/learn/test_simhash.py
zounds/learn/test_sklearn_preprocessor.py
zounds/learn/test_slicer.py
zounds/learn/test_unitnorm.py
