Metadata-Version: 1.1
Name: zounds
Version: 1.54.0
Summary: UNKNOWN
Home-page: https://github.com/JohnVinyard/zounds
Author: John Vinyard
Author-email: john.vinyard@gmail.com
License: UNKNOWN
Download-URL: https://github.com/jvinyard/zounds/tarball/1.54.0
Platform: UNKNOWN
Classifier: Programming Language :: Python :: 3
